qualg/__init__.py
qualg/fock_state.py
qualg/integrate.py
qualg/measure.py
qualg/operators.py
qualg/q_state.py
qualg/scalars.py
qualg/states.py
qualg/toolbox.py
qualg-0.1.0.dist-info/LICENSE
qualg-0.1.0.dist-info/METADATA
qualg-0.1.0.dist-info/WHEEL
qualg-0.1.0.dist-info/top_level.txt
qualg-0.1.0.dist-info/RECORD
