Metadata-Version: 2.1
Name: qualg
Version: 0.1.0
Summary: Symbolic linear algrebra for quantum mechanics
Home-page: https://github.com/AckslD/QuAlg
Author: Axel Dahlberg
Author-email: axel.dahlberg12@gmail.com
License: UNKNOWN
Platform: UNKNOWN
Requires-Python: >=3.6
Requires-Dist: numpy
